HCNetSDK/HCNetSDK.py
HCNetSDK/SDK_Callback.py
HCNetSDK/SDK_Enum.py
HCNetSDK/SDK_Struct.py
HCNetSDK/__init__.py
HCNetSDK/Libs/linux/HCNetSDK_Log_Switch.xml
HCNetSDK/Libs/linux/libAudioRender.so
HCNetSDK/Libs/linux/libHCCore.so
HCNetSDK/Libs/linux/libNPQos.so
HCNetSDK/Libs/linux/libPlayCtrl.so
HCNetSDK/Libs/linux/libSuperRender.so
HCNetSDK/Libs/linux/libcrypto.so.1.1
HCNetSDK/Libs/linux/libhcnetsdk.so
HCNetSDK/Libs/linux/libhpr.so
HCNetSDK/Libs/linux/libopenal.so.1
HCNetSDK/Libs/linux/libssl.so.1.1
HCNetSDK/Libs/linux/libz.so
HCNetSDK/Libs/linux/HCNetSDKCom/libAudioIntercom.so
HCNetSDK/Libs/linux/HCNetSDKCom/libHCAlarm.so
HCNetSDK/Libs/linux/HCNetSDKCom/libHCCoreDevCfg.so
HCNetSDK/Libs/linux/HCNetSDKCom/libHCDisplay.so
HCNetSDK/Libs/linux/HCNetSDKCom/libHCGeneralCfgMgr.so
HCNetSDK/Libs/linux/HCNetSDKCom/libHCIndustry.so
HCNetSDK/Libs/linux/HCNetSDKCom/libHCPlayBack.so
HCNetSDK/Libs/linux/HCNetSDKCom/libHCPreview.so
HCNetSDK/Libs/linux/HCNetSDKCom/libHCVoiceTalk.so
HCNetSDK/Libs/linux/HCNetSDKCom/libStreamTransClient.so
HCNetSDK/Libs/linux/HCNetSDKCom/libSystemTransform.so
HCNetSDK/Libs/linux/HCNetSDKCom/libanalyzedata.so
HCNetSDK/Libs/linux/HCNetSDKCom/libiconv2.so
HCNetSDK/Libs/log/.keep
HCNetSDK_python-1.0.0.dist-info/LICENSE
HCNetSDK_python-1.0.0.dist-info/METADATA
HCNetSDK_python-1.0.0.dist-info/WHEEL
HCNetSDK_python-1.0.0.dist-info/top_level.txt
HCNetSDK_python-1.0.0.dist-info/RECORD
